dns_insight_extractor/__init__.py
dns_insight_extractor/main.py
dns_insight_extractor/prompts.py
dns_insight_extractor-2025.12.21174113.dist-info/METADATA
dns_insight_extractor-2025.12.21174113.dist-info/WHEEL
dns_insight_extractor-2025.12.21174113.dist-info/top_level.txt
dns_insight_extractor-2025.12.21174113.dist-info/RECORD
