Metadata-Version: 2.4
Name: dns-insight-extractor
Version: 2025.12.21174113
Summary: This new package facilitates extracting structured insights from text-based content related to domain-specific issues, such as analyzing DNS blocking reports. Given unstructured text describing networ
Author-email: dns-insight-extractor <hi@eugene.plus>
License: MIT
Project-URL: Homepage, https://github.com/chigwell/dns-insight-extractor
Requires-Python: >=3.9
Requires-Dist: langchain-llm7>=0.0.0
Requires-Dist: llmatch-messages>=0.0.0
Requires-Dist: langchain-core>=0.3.0
